README.md
setup.py
Pi20English/KumandaKontrol.py
Pi20English/MotorKontrol.py
Pi20English/PiKamera20.py
Pi20English/ServoKontrol.py
Pi20English/UltrasonikSensor.py
Pi20English/__init__.py
Pi20English/pololu_drv8835_rpi.py
Pi20English.egg-info/PKG-INFO
Pi20English.egg-info/SOURCES.txt
Pi20English.egg-info/dependency_links.txt
Pi20English.egg-info/requires.txt
Pi20English.egg-info/top_level.txt