Metadata-Version: 1.1
Name: Pi20English
Version: 1.0
Summary: Library that makes use of sensors, motors, and servos in the PiWars Turkey robot kit by HisarCS
Home-page: UNKNOWN
Author: Andy Emre Kocak, Rana Taki, Yoel Kastro, Yasar Idikut
Author-email: emre.kocak@hisarschool.k12.tr, rana.taki@hisarschool.k12.tr, sarp.kastro@hisarschool.k12.tr, yasar.idikut@hisarschool.k12.tr
License: UNKNOWN
Platform: UNKNOWN
Classifier: Development Status :: 4 - Beta
